{
	"isvProtocol":{
		"method":"POST|GET",
		"protocol":"HTTP|HTTPS"
	},
	"name":"DescribeOptimizeAdviceOnExcessIndex",
	"parameters":{
		"parameters":[
			{
				"required":"false",
				"tagName":"OwnerId",
				"tagPosition":"Query",
				"type":"Long",
				"valueSwitch":{
					
				}
			},
			{
				"required":"false",
				"tagName":"ResourceOwnerAccount",
				"tagPosition":"Query",
				"type":"String",
				"valueSwitch":{
					
				}
			},
			{
				"required":"false",
				"tagName":"ResourceOwnerId",
				"tagPosition":"Query",
				"type":"Long",
				"valueSwitch":{
					
				}
			},
			{
				"required":"true",
				"tagName":"DBInstanceId",
				"tagPosition":"Query",
				"type":"String",
				"valueSwitch":{
					
				}
			},
			{
				"maxValue":"100",
				"minValue":"30",
				"required":"false",
				"tagName":"PageSize",
				"tagPosition":"Query",
				"type":"Integer",
				"valueSwitch":{
					
				}
			},
			{
				"maxValue":"2147483647",
				"minValue":"1",
				"required":"false",
				"tagName":"PageNumber",
				"tagPosition":"Query",
				"type":"Integer",
				"valueSwitch":{
					
				}
			},
			{
				"required":"false",
				"tagName":"OwnerAccount",
				"tagPosition":"Query",
				"type":"String",
				"valueSwitch":{
					
				}
			}
		]
	},
	"product":"Rds",
	"resultMapping":{
		"arrays":[
			{
				"itemName":"AdviceOnExcessIndex",
				"members":[
					{
						"tagName":"DBName",
						"type":"String"
					},
					{
						"tagName":"TableName",
						"type":"String"
					},
					{
						"tagName":"IndexCount",
						"type":"Long"
					}
				],
				"tagName":"Items"
			}
		],
		"members":[
			{
				"tagName":"TotalRecordsCount",
				"type":"Integer"
			},
			{
				"tagName":"PageNumber",
				"type":"Integer"
			},
			{
				"tagName":"PageRecordCount",
				"type":"Integer"
			}
		]
	},
	"version":"2014-08-15"
}
