{
	"isvProtocol":{
		"method":"POST|GET",
		"protocol":"HTTP|HTTPS"
	},
	"name":"DescribeLoadBalancers",
	"parameters":{
		"parameters":[
			{
				"required":"false",
				"tagName":"OwnerId",
				"tagPosition":"Query",
				"type":"Long",
				"valueSwitch":{
					
				}
			},
			{
				"required":"false",
				"tagName":"ResourceOwnerAccount",
				"tagPosition":"Query",
				"type":"String",
				"valueSwitch":{
					
				}
			},
			{
				"required":"false",
				"tagName":"ResourceOwnerId",
				"tagPosition":"Query",
				"type":"Long",
				"valueSwitch":{
					
				}
			},
			{
				"required":"false",
				"tagName":"ServerId",
				"tagPosition":"Query",
				"type":"String",
				"valueSwitch":{
					
				}
			},
			{
				"required":"false",
				"tagName":"LoadBalancerId",
				"tagPosition":"Query",
				"type":"String",
				"valueSwitch":{
					
				}
			},
			{
				"required":"false",
				"tagName":"AddressType",
				"tagPosition":"Query",
				"type":"String",
				"valueSwitch":{
					
				}
			},
			{
				"required":"false",
				"tagName":"InternetChargeType",
				"tagPosition":"Query",
				"type":"String",
				"valueSwitch":{
					
				}
			},
			{
				"required":"false",
				"tagName":"VpcId",
				"tagPosition":"Query",
				"type":"String",
				"valueSwitch":{
					
				}
			},
			{
				"required":"false",
				"tagName":"VSwitchId",
				"tagPosition":"Query",
				"type":"String",
				"valueSwitch":{
					
				}
			},
			{
				"required":"false",
				"tagName":"NetworkType",
				"tagPosition":"Query",
				"type":"String",
				"valueSwitch":{
					
				}
			},
			{
				"required":"false",
				"tagName":"Address",
				"tagPosition":"Query",
				"type":"String",
				"valueSwitch":{
					
				}
			},
			{
				"required":"false",
				"tagName":"SecurityStatus",
				"tagPosition":"Query",
				"type":"String",
				"valueSwitch":{
					
				}
			},
			{
				"required":"false",
				"tagName":"MasterZoneId",
				"tagPosition":"Query",
				"type":"String",
				"valueSwitch":{
					
				}
			},
			{
				"required":"false",
				"tagName":"SlaveZoneId",
				"tagPosition":"Query",
				"type":"String",
				"valueSwitch":{
					
				}
			},
			{
				"required":"false",
				"tagName":"OwnerAccount",
				"tagPosition":"Query",
				"type":"String",
				"valueSwitch":{
					
				}
			}
		]
	},
	"product":"Slb",
	"resultMapping":{
		"arrays":[
			{
				"itemName":"LoadBalancer",
				"members":[
					{
						"tagName":"LoadBalancerId",
						"type":"String"
					},
					{
						"tagName":"LoadBalancerName",
						"type":"String"
					},
					{
						"tagName":"LoadBalancerStatus",
						"type":"String"
					},
					{
						"tagName":"Address",
						"type":"String"
					},
					{
						"tagName":"AddressType",
						"type":"String"
					},
					{
						"tagName":"RegionId",
						"type":"String"
					},
					{
						"tagName":"RegionIdAlias",
						"type":"String"
					},
					{
						"tagName":"VSwitchId",
						"type":"String"
					},
					{
						"tagName":"VpcId",
						"type":"String"
					},
					{
						"tagName":"NetworkType",
						"type":"String"
					},
					{
						"tagName":"MasterZoneId",
						"type":"String"
					},
					{
						"tagName":"SlaveZoneId",
						"type":"String"
					},
					{
						"tagName":"MaxConnLimit",
						"type":"Integer"
					},
					{
						"tagName":"SecurityStatus",
						"type":"String"
					},
					{
						"tagName":"InternetChargeType",
						"type":"String"
					},
					{
						"tagName":"SysBandwidth",
						"type":"Integer"
					}
				],
				"tagName":"LoadBalancers"
			}
		],
		"members":[
			
		]
	},
	"version":"2014-05-15"
}
