{
	"apiStyle":"ROA",
	"apis":{
		"apis":[
			{
				"name":"StopJob"
			},
			{
				"name":"StartJob"
			},
			{
				"name":"ReleaseJob"
			},
			{
				"name":"PutJob"
			},
			{
				"name":"PostJob"
			},
			{
				"name":"ListSnapshots"
			},
			{
				"name":"ListJobs"
			},
			{
				"name":"ListImages"
			},
			{
				"name":"GetTasks"
			},
			{
				"name":"GetJobDescription"
			},
			{
				"name":"GetJob"
			},
			{
				"name":"DeleteJob"
			}
		]
	},
	"name":"2015-06-30",
	"product":"BatchCompute"
}
